[
  {
    "n": "2024-2-1-(2)",
    "q": "募集型企画旅行契約の部「旅行契約の内容」「手配代行者」「契約の申込み」「電話等による予約」に関する次の記述のうち、正しいものを1つ選びなさい。",
    "o": [
      [
        "旅行業者は、旅行者が契約の申込みの際に支払った申込金を、旅行代金又は取消料の一部として取り扱い、他に充当することはできない。",
        "申込金は、旅行代金、取消料のほか「違約料」の一部としても取り扱われます。(標準旅行業約款 募集型企画旅行契約の部 第5条第3項)\n"
      ],
      [
        "旅行業者は、契約において、旅行者が旅行業者の定める旅行日程に従って、運送・宿泊機関等の提供する運送、宿泊その他の旅行に関するサービスの提供を受けることができるように、手配することのみを引き受ける。",
        "募集型企画旅行契約では、旅行サービスの手配だけでなく、「旅程を管理すること」も引き受けます。(標準旅行業約款 募集型企画旅行契約の部 第3条第1項)\n"
      ],
      [
        "旅行業者は、国内旅行の契約の履行に当たって、手配の全部又は一部を手配を業として行う者に代行させることはできない。",
        "国内旅行の契約履行にあたり、手配の全部または一部を他の事業者などに代行させることができます。(標準旅行業約款 募集型企画旅行契約の部 第4条)\n"
      ],
      [
        "旅行業者が旅行者からインターネットにより通信契約の予約を受け付け、当該予約の承諾の旨を通知した後、旅行業者が定める期間内に、当該旅行者から会員番号等の通知があったときは、契約の締結の順位は、当該予約の受付の順位による。",
        "電話やインターネット等による予約の場合、予約承諾後に申込手続きが完了した時点で、予約受付の順位で契約が成立します。これは正しい記述です。(標準旅行業約款 募集型企画旅行契約の部 第6条)\n"
      ]
    ],
    "a": [
      3
    ],
    "e": "- 申込金は旅行代金、取消料、違約料の一部として扱われます。\n- 募集型企画旅行では、手配と旅程管理の両方を引き受けます。\n- 手配の代行は可能です。\n- 予約受付の場合、契約締結の順位は予約の受付順となります。"
  }
]