[
  {
    "n": "2023-1-(13)",
    "q": "旅行業務取扱管理者の証明書の提示、外務員の証明書携帯等に関する次の記述のうち、正しいものはどれか。",
    "o": [
      [
        "旅行業者代理業者の外務員の証明書は、必ず当該旅行業者代理業者の所属旅行業者が発行しなければならない。",
        "外務員の証明書は、所属する旅行業者等(この場合は旅行業者代理業者自身)が発行するものであり、所属旅行業者(親会社)が発行するものではない。\n"
      ],
      [
        "旅行業務取扱管理者が、旅行業務について旅行者と契約を締結しようとするときは、旅行者に対し、国土交通省令で定める様式による旅行業務取扱管理者の証明書を必ず提示しなければならない。",
        "「必ず提示」ではなく、「旅行者から請求があったとき」に提示義務が生じる。\n"
      ],
      [
        "外務員とは、勧誘員、販売員、外交員その他いかなる名称を有する者であるかを問わず、旅行業者等の役員又は使用人のうち、その営業所以外の場所でその旅行業者等のために旅行業務について取引を行う者をいう。",
        "旅行業法第12条の6第1項の定義通り。これは正しい記述です。\n"
      ],
      [
        "外務員は、いかなる場合においても、その所属する旅行業者等に代わって、旅行者との旅行業務に関する取引についての一切の裁判外の行為を行う権限を有するものとみなされる。",
        "「いかなる場合においても」ではなく、「旅行者が悪意であったときを除き」というただし書きがある。\n"
      ]
    ],
    "a": [
      2
    ],
    "e": "[旅行業務取扱管理者の証明書(旅行業法第12条の5の2)]\n- 旅行業務取扱管理者は、旅行者から請求があったときは、国土交通省令で定める様式による証明書を提示しなければならない。\n- 「必ず提示しなければならない」わけではなく、「請求があったとき」に提示義務が生じる。\n\n[外務員(旅行業法第12条の6)]\n- 外務員とは、営業所以外の場所で旅行業者等のために旅行業務について取引を行う役員または使用人を指す(第12条の6第1項)。\n- 外務員には、国土交通省令で定める様式による証明書を携帯させなければならない(第12条の6第1項)。\n- 外務員は、その業務を行うときは、証明書を提示しなければならない(第12条の6第2項)。\n- 外務員は、その所属する旅行業者等に代わって、旅行者との旅行業務に関する取引についての一切の裁判外の行為を行う権限を有するものとみなされる。ただし、旅行者が悪意であったときはこの限りでない(第12条の6第3項)。\n- 外務員の証明書は、所属する旅行業者等が発行する。\n\n重要ポイント:\n[管理者と外務員の区別]\n- 管理者: 請求があったら証明書を提示。\n- 外務員: 営業所以外で業務を行う者。証明書携帯・提示義務あり。悪意の旅行者以外には代理権があるとみなされる。\n\n[証明書の発行元]\n- 外務員証は、所属する旅行業者等自身が発行する。\n\n覚え方のコツ:\n「管理者は『請求されたら』見せる、外務員は『常に携帯』して『見せる』」\n「外務員は会社の『顔』、だから代理権がある」"
  }
]